LICENSE
README.rst
climatecontrol/__init__.py
climatecontrol/cli_utils.py
climatecontrol/constants.py
climatecontrol/core.py
climatecontrol/env_parser.py
climatecontrol/exceptions.py
climatecontrol/ext/__init__.py
climatecontrol/ext/dataclasses.py
climatecontrol/ext/pydantic.py
climatecontrol/file_loaders.py
climatecontrol/fragment.py
climatecontrol/logtools.py
climatecontrol/processors.py
climatecontrol/py.typed
climatecontrol/utils.py
setup.py
climatecontrol-0.11.0.dist-info/LICENSE
climatecontrol-0.11.0.dist-info/WHEEL
climatecontrol-0.11.0.dist-info/METADATA
climatecontrol-0.11.0.dist-info/RECORD
