Metadata-Version: 2.1
Name: climatecontrol
Version: 0.11.0
Summary: Python library for loading app configurations from files and/or namespaced environment variables.
Home-page: https://github.com/daviskirk/climatecontrol
License: MIT
Keywords: climatecontrol,configuration,environment
Author: Davis Kirkendall
Author-email: davis.e.kirkendall@gmail.com
Requires-Python: >=3.7,<4.0
Classifier: Development Status :: 4 - Beta
Classifier: Intended Audience :: Developers
Classifier: License :: OSI Approved :: MIT License
Classifier: Natural Language :: English
Classifier: Operating System :: OS Independent
Classifier: Programming Language :: Python :: 3
Classifier: Programming Language :: Python :: 3.10
Classifier: Programming Language :: Python :: 3.7
Classifier: Programming Language :: Python :: 3.8
Classifier: Programming Language :: Python :: 3.9
Classifier: Topic :: Software Development :: Libraries
Classifier: Topic :: Software Development :: Libraries :: Python Modules
Classifier: Topic :: Utilities
Provides-Extra: dataclasses
Requires-Dist: dacite (>=1.6,<2.0); extra == "dataclasses"
Requires-Dist: pydantic (>=1.7.4,<2.0.0); extra == "dataclasses"
Requires-Dist: wrapt (>=1.12,<2.0)
Project-URL: Documentation, https://github.com/daviskirk/climatecontrol
Project-URL: Repository, https://github.com/daviskirk/climatecontrol
